{"noiseKey":{"private":{"type":"Buffer","data":"CMTWf5uljDhH9KCNYStHiOLpir6UPRePrgVU3/RTsn8="},"public":{"type":"Buffer","data":"1eLI+k4MxYExbsBMNS4TNWP4H96RZ25cok8rg7xPNmw="}},"pairingEphemeralKeyPair":{"private":{"type":"Buffer","data":"0PinAnJ19+e/aga32hF2P3VsAUxfV56MlOdYwOE6YHw="},"public":{"type":"Buffer","data":"XzFot4U/Frk0ytQ0AQ+LpnV57yKoddHT5cmQB0i07k8="}},"signedIdentityKey":{"private":{"type":"Buffer","data":"uF4LAyxIyGPu1DEM2ZB6rztMJ7QCkc1rcnMvTpfw8Go="},"public":{"type":"Buffer","data":"OrJRex6LLqqwX7uSX9VYCMwFqMvlgxb9nNXnI/5Kf0M="}},"signedPreKey":{"keyPair":{"private":{"type":"Buffer","data":"yL/fbcn8NtI69K79PDfdncx8LYMd6mvMp3jbAM376nA="},"public":{"type":"Buffer","data":"0TSdTBdb1YOcbSrgy6+nZ0DOi9UVnP8VSnAFQUFfbUY="}},"signature":{"type":"Buffer","data":"8aiRoCPv5Nkkc+vgMdUUeyGwJJXsomVBDBP+oW9ZauB9K7bS1o3fRj7v71inIDRpQFbWvOx64HEWGg3+U5gJhg=="},"keyId":1},"registrationId":155,"advSecretKey":"HUOlgHPAuipjXDJCnF/qi/DxkG1F/bSMjTE6nWWR2fU=","processedHistoryMessages":[{"key":{"remoteJid":"2347044625110@s.whatsapp.net","fromMe":false,"id":"3AF3656C4C9520D513F7","participant":"","addressingMode":"pn"},"messageTimestamp":1777040593},{"key":{"remoteJid":"2347044625110@s.whatsapp.net","fromMe":false,"id":"3A866254AF2C18837C1F","participant":"","addressingMode":"pn"},"messageTimestamp":1777040611},{"key":{"remoteJid":"2347044625110@s.whatsapp.net","fromMe":false,"id":"3AF0DDAD33E2D9216BA3","participant":"","addressingMode":"pn"},"messageTimestamp":1777040640},{"key":{"remoteJid":"2347044625110@s.whatsapp.net","fromMe":false,"id":"3AA76FE5438BE0775AE2","participant":"","addressingMode":"pn"},"messageTimestamp":1777040700},{"key":{"remoteJid":"2347044625110@s.whatsapp.net","fromMe":false,"id":"3A299D54F1E336993908","participant":"","addressingMode":"pn"},"messageTimestamp":1777040723},{"key":{"remoteJid":"2347044625110@s.whatsapp.net","fromMe":false,"id":"3AB2EE7345BD7CFC06F6","participant":"","addressingMode":"pn"},"messageTimestamp":1777040739},{"key":{"remoteJid":"2347044625110@s.whatsapp.net","fromMe":false,"id":"3A0010AE80313044ABEE","participant":"","addressingMode":"pn"},"messageTimestamp":1777040804},{"key":{"remoteJid":"2347044625110@s.whatsapp.net","fromMe":false,"id":"3A91EAC8035796FEB90D","participant":"","addressingMode":"pn"},"messageTimestamp":1777040811},{"key":{"remoteJid":"2347044625110@s.whatsapp.net","fromMe":false,"id":"3ACC79BB2ECEBFADA3C6","participant":"","addressingMode":"pn"},"messageTimestamp":1777040826},{"key":{"remoteJid":"2347044625110@s.whatsapp.net","fromMe":false,"id":"3A7B672C42A8C49FB287","participant":"","addressingMode":"pn"},"messageTimestamp":1777040826},{"key":{"remoteJid":"2347044625110@s.whatsapp.net","fromMe":false,"id":"3A53116183ACE9AA71F8","participant":"","addressingMode":"pn"},"messageTimestamp":1777040834},{"key":{"remoteJid":"2347044625110@s.whatsapp.net","fromMe":false,"id":"3A659576D01750EF6D19","participant":"","addressingMode":"pn"},"messageTimestamp":1777040851},{"key":{"remoteJid":"2347044625110@s.whatsapp.net","fromMe":false,"id":"3ACB8BD6683253601AEC","participant":"","addressingMode":"pn"},"messageTimestamp":1777040859},{"key":{"remoteJid":"2347044625110@s.whatsapp.net","fromMe":false,"id":"3A5F7858F01E66B43BEE","participant":"","addressingMode":"pn"},"messageTimestamp":1777040859},{"key":{"remoteJid":"2347044625110@s.whatsapp.net","fromMe":false,"id":"3AD668D1AEC26CA0CCC9","participant":"","addressingMode":"pn"},"messageTimestamp":1777040867}],"nextPreKeyId":814,"firstUnuploadedPreKeyId":814,"accountSyncCounter":2,"accountSettings":{"unarchiveChats":false},"registered":false,"account":{"details":"CMrxkLENELj5rc8GGEggACgA","accountSignatureKey":"bJ+AAwge2ViTAyqVizKrqof7vUhdYhVyJK9XLk9MpXM=","accountSignature":"19XSLFyYEuKR9SizAoahB46v/cpoER5NxC2HZo8pc5YE9tM5EX1In7l25lp6/A5D9n7YQ/Kk7dM84nkT3/Mciw==","deviceSignature":"RenEPt8ZX+qLiY8ZMybCDDyqlYRD9tyCej3yWI7EM5KQwNnq8vd6xi/MQstO8pq2ztb1hHkM3ol+zg/zJ+7/hw=="},"me":{"id":"2347044625110:43@s.whatsapp.net","lid":"231585072828587:43@lid","name":"Gibborlee🧠"},"signalIdentities":[{"identifier":{"name":"231585072828587:43@lid","deviceId":0},"identifierKey":{"type":"Buffer","data":"BWyfgAMIHtlYkwMqlYsyq6qH+71IXWIVciSvVy5PTKVz"}}],"platform":"iphone","routingInfo":{"type":"Buffer","data":"CAsICQgF"},"lastAccountSyncTimestamp":1777040867,"myAppStateKeyId":"AAAAAB0x"}